tghandler/__init__.py
tghandler/handler.py
aio_telegram_log_handler-1.0.1.dist-info/METADATA
aio_telegram_log_handler-1.0.1.dist-info/WHEEL
aio_telegram_log_handler-1.0.1.dist-info/top_level.txt
aio_telegram_log_handler-1.0.1.dist-info/RECORD
