Metadata-Version: 2.1
Name: aio-telegram-log-handler
Version: 1.0.1
Summary: Package for send some important logs directly to telegram
Author: Daniil Solynin
Author-email: Daniil Solynin <solynynd@gmail.com>
Keywords: telegram,logging,async
Classifier: Programming Language :: Python :: 3
Requires-Python: >=3.9
Requires-Dist: aiohttp (>=3.8.4)
Provides-Extra: linters
Requires-Dist: isort ; extra == 'linters'
Requires-Dist: mypy ; extra == 'linters'
Requires-Dist: black ; extra == 'linters'
Provides-Extra: test
Requires-Dist: pytest (>=7) ; extra == 'test'
Requires-Dist: pytest-asyncio (>=0.21) ; extra == 'test'
